<?xml version="1.0" encoding="UTF-8"?>
<tv generator-info-name="WebGrab+Plus/w MDB &amp; REX Postprocess -- version V3.1.2.0 -- Jan van Straaten" generator-info-url="http://www.webgrabplus.com">
  <channel id="pluto-tv-kids">
    <display-name lang="es">Pluto TV Kids</display-name>
  </channel>
  <channel id="pluto-tv-news">
    <display-name lang="es">Pluto TV News</display-name>
  </channel>
  <channel id="slow-tv">
    <display-name lang="es">Slow TV</display-name>
  </channel>
  <channel id="tyt-network">
    <display-name lang="es">TYT Network</display-name>
  </channel>
  <channel id="glory-kickboxing">
    <display-name lang="es">GLORY Kickboxing</display-name>
  </channel>
  <channel id="cnn">
    <display-name lang="es">CNN</display-name>
  </channel>
  <channel id="mst3k">
    <display-name lang="es">MST3K</display-name>
  </channel>
  <channel id="newsy">
    <display-name lang="es">Top Stories by Newsy</display-name>
  </channel>
  <channel id="nasa-tv">
    <display-name lang="es">NASA TV</display-name>
  </channel>
  <channel id="bloomberg-tv">
    <display-name lang="es">Bloomberg TV</display-name>
  </channel>
  <channel id="failarmy">
    <display-name lang="es">FailArmy</display-name>
  </channel>
  <channel id="awesomenesstv">
    <display-name lang="es">Awesomeness TV</display-name>
  </channel>
  <channel id="shout-factory-tv">
    <display-name lang="es">Shout! Factory TV</display-name>
  </channel>
  <channel id="newsmax-tv">
    <display-name lang="es">NewsmaxTV</display-name>
  </channel>
  <channel id="sky-news">
    <display-name lang="es">Sky News</display-name>
  </channel>
  <channel id="world-poker-tour">
    <display-name lang="es">World Poker Tour</display-name>
  </channel>
  <channel id="after-school-cartoons">
    <display-name lang="es">After School Cartoons</display-name>
  </channel>
  <channel id="classic-movies-channel">
    <display-name lang="es">Classic Movies Channel</display-name>
  </channel>
  <channel id="ign">
    <display-name lang="es">IGN</display-name>
  </channel>
  <channel id="pluto-tv-action">
    <display-name lang="es">Pluto TV Action</display-name>
  </channel>
  <channel id="cnet">
    <display-name lang="es">CNET</display-name>
  </channel>
  <channel id="classic-toons-tv">
    <display-name lang="es">Classic Toons TV</display-name>
  </channel>
  <channel id="pluto-tv-sports">
    <display-name lang="es">Pluto TV Sports</display-name>
  </channel>
  <channel id="stand-up-tv">
    <display-name lang="es">Stand-Up TV</display-name>
  </channel>
  <channel id="pluto-tv-science">
    <display-name lang="es">Pluto TV Science</display-name>
  </channel>
  <channel id="pluto-tv-horror">
    <display-name lang="es">Pluto TV Horror</display-name>
  </channel>
  <channel id="pluto-tv-animals">
    <display-name lang="es">Pluto TV Animals</display-name>
  </channel>
  <channel id="funny-af">
    <display-name lang="es">Funny AF</display-name>
  </channel>
  <channel id="cheddar-1">
    <display-name lang="es">Cheddar</display-name>
  </channel>
  <channel id="fight">
    <display-name lang="es">Fight</display-name>
  </channel>
  <channel id="cars">
    <display-name lang="es">Pluto TV Cars</display-name>
  </channel>
  <channel id="anime-all-day">
    <display-name lang="es">Anime All Day</display-name>
  </channel>
  <channel id="minecraftv">
    <display-name lang="es">MinecrafTV</display-name>
  </channel>
  <channel id="spike">
    <display-name lang="es">Spike Pluto TV</display-name>
  </channel>
  <channel id="naturescape">
    <display-name lang="es">Naturescape</display-name>
  </channel>
  <channel id="pluto-tv-true-crime">
    <display-name lang="es">Pluto TV True Crime</display-name>
  </channel>
  <channel id="buzzr">
    <display-name lang="es">BUZZR</display-name>
  </channel>
  <channel id="live-music-replay">
    <display-name lang="es">Live Music Replay</display-name>
  </channel>
  <channel id="food-tv">
    <display-name lang="es">Food TV</display-name>
  </channel>
  <channel id="pluto-tv-weddings">
    <display-name lang="es">Pluto TV Weddings</display-name>
  </channel>
  <channel id="fear-factor">
    <display-name lang="es">Fear Factor</display-name>
  </channel>
  <channel id="pluto-tv-best-life">
    <display-name lang="es">Pluto TV Best Life</display-name>
  </channel>
  <channel id="xive-tv">
    <display-name lang="es">Voyager Documentaries</display-name>
  </channel>
  <channel id="black-cinema">
    <display-name lang="es">Black Cinema</display-name>
  </channel>
  <channel id="rifftrax">
    <display-name lang="es">RiffTrax</display-name>
  </channel>
  <channel id="flicks-of-fury">
    <display-name lang="es">Flicks of Fury</display-name>
  </channel>
  <channel id="the-asylum">
    <display-name lang="es">The Asylum</display-name>
  </channel>
  <channel id="adventure-tv">
    <display-name lang="es">Adventure TV</display-name>
  </channel>
  <channel id="frontdoor">
    <display-name lang="es">FrontDoor</display-name>
  </channel>
  <channel id="big-sky-conference">
    <display-name lang="es">Big Sky Conference</display-name>
  </channel>
  <channel id="cats-247">
    <display-name lang="es">Cats 24/7</display-name>
  </channel>
  <channel id="stadium">
    <display-name lang="es">Stadium</display-name>
  </channel>
  <channel id="impact-wrestling-channel">
    <display-name lang="es">IMPACT Wrestling</display-name>
  </channel>
  <channel id="pluto-tv-travel">
    <display-name lang="es">Pluto TV Travel</display-name>
  </channel>
  <channel id="people-tv">
    <display-name lang="es">PeopleTV</display-name>
  </channel>
  <channel id="pluto-tv-history">
    <display-name lang="es">Pluto TV History</display-name>
  </channel>
  <channel id="pluto-tv-comedy">
    <display-name lang="es">Pluto TV Comedy</display-name>
  </channel>
  <channel id="pluto-tv-romance">
    <display-name lang="es">Pluto TV Romance</display-name>
  </channel>
  <channel id="cbsn-2">
    <display-name lang="es">CBSN 2</display-name>
  </channel>
  <channel id="fox-sports">
    <display-name lang="es">FOX Sports</display-name>
  </channel>
  <channel id="wipeout">
    <display-name lang="es">Wipeout</display-name>
  </channel>
  <channel id="pluto-tv-paranormal">
    <display-name lang="es">Pluto TV Paranormal</display-name>
  </channel>
  <channel id="the-new-detectives">
    <display-name lang="es">The New Detectives</display-name>
  </channel>
  <channel id="nosey">
    <display-name lang="es">Nosey</display-name>
  </channel>
  <channel id="laughoutloud">
    <display-name lang="es">Kevin Hart LOL</display-name>
  </channel>
  <channel id="red-bull-tv-2">
    <display-name lang="es">Red Bull TV</display-name>
  </channel>
  <channel id="dogs-247">
    <display-name lang="es">Dogs 24/7</display-name>
  </channel>
  <channel id="privacy-policy">
    <display-name lang="es">Privacy Policy</display-name>
  </channel>
  <channel id="pluto-tv-thrillers">
    <display-name lang="es">Pluto TV Thrillers</display-name>
  </channel>
  <channel id="pluto-tv-drama">
    <display-name lang="es">Pluto TV Drama</display-name>
  </channel>
  <channel id="cmt-westerns">
    <display-name lang="es">CMT Westerns</display-name>
  </channel>
  <channel id="unsolved-mysteries">
    <display-name lang="es">Unsolved Mysteries</display-name>
  </channel>
  <channel id="gordon-ramsay's-kitchen">
    <display-name lang="es">Gordon Ramsay's Kitchen</display-name>
  </channel>
  <channel id="pluto-tv-sci-fi">
    <display-name lang="es">Pluto TV Sci-Fi</display-name>
  </channel>
  <channel id="pluto-tv-fantastic">
    <display-name lang="es">Pluto TV Fantastic</display-name>
  </channel>
  <channel id="british-tv">
    <display-name lang="es">British TV</display-name>
  </channel>
  <channel id="chassy">
    <display-name lang="es">Chassy</display-name>
  </channel>
  <channel id="pluto-tv-documentaries">
    <display-name lang="es">Pluto TV Documentaries</display-name>
  </channel>
  <channel id="pluto-tv-spotlight">
    <display-name lang="es">Pluto TV Spotlight</display-name>
  </channel>
  <channel id="combate-world">
    <display-name lang="es">Combate World</display-name>
  </channel>
  <channel id="the-pet-collective">
    <display-name lang="es">The Pet Collective</display-name>
  </channel>
  <channel id="forensic-files">
    <display-name lang="es">Forensic Files</display-name>
  </channel>
  <channel id="complex-networks">
    <display-name lang="es">Complex Networks</display-name>
  </channel>
  <channel id="pluto-tv-military">
    <display-name lang="es">Pluto TV Military</display-name>
  </channel>
  <channel id="pluto-tv-election">
    <display-name lang="es">Pluto TV Election</display-name>
  </channel>
  <channel id="weather-nation">
    <display-name lang="es">WeatherNation</display-name>
  </channel>
  <channel id="dog-the-bounty-hunter">
    <display-name lang="es">Dog the Bounty Hunter</display-name>
  </channel>
  <channel id="lucha-libre-aaa">
    <display-name lang="es">Lucha Libre AAA</display-name>
  </channel>
  <channel id="tv-land-sitcoms">
    <display-name lang="es">TV Land Sitcoms</display-name>
  </channel>
  <channel id="pluto-tv-biography">
    <display-name lang="es">Pluto TV Biography</display-name>
  </channel>
  <channel id="cold-case-files">
    <display-name lang="es">Cold Case Files</display-name>
  </channel>
  <channel id="spike-outdoors">
    <display-name lang="es">Spike Outdoors</display-name>
  </channel>
  <channel id="tokushoutsu">
    <display-name lang="es">TokuSHOUTsu</display-name>
  </channel>
  <channel id="faith-tv">
    <display-name lang="es">Faith TV</display-name>
  </channel>
  <channel id="pluto-tv-cult-films">
    <display-name lang="es">Pluto TV Cult Films</display-name>
  </channel>
  <channel id="pluto-tv-terror">
    <display-name lang="es">Pluto TV Terror</display-name>
  </channel>
  <channel id="degrassi">
    <display-name lang="es">Degrassi</display-name>
  </channel>
  <channel id="80s-rewind">
    <display-name lang="es">80s Rewind</display-name>
  </channel>
  <channel id="bet-pluto-tv">
    <display-name lang="es">BET Pluto TV</display-name>
  </channel>
  <channel id="comedy-central-pluto-tv">
    <display-name lang="es">Comedy Central Pluto TV</display-name>
  </channel>
  <channel id="mtv-pluto-tv">
    <display-name lang="es">MTV Pluto TV</display-name>
  </channel>
  <channel id="nick-pluto-tv">
    <display-name lang="es">Nick Pluto TV</display-name>
  </channel>
  <channel id="nick-jr.-pluto-tv">
    <display-name lang="es">Nick Jr. Pluto TV</display-name>
  </channel>
  <channel id="comedy-central-stand-up">
    <display-name lang="es">Comedy Central Stand-Up</display-name>
  </channel>
  <channel id="mtv-dating">
    <display-name lang="es">MTV Dating</display-name>
  </channel>
  <channel id="pluto-tv-gamer">
    <display-name lang="es">Pluto TV Gamer</display-name>
  </channel>
  <channel id="pluto-tv-backcountry">
    <display-name lang="es">Pluto TV Backcountry</display-name>
  </channel>
  <channel id="paramount-movie-channel">
    <display-name lang="es">Paramount Movie Channel</display-name>
  </channel>
  <channel id="mls">
    <display-name lang="es">MLS</display-name>
  </channel>
  <channel id="midsomer-murders">
    <display-name lang="es">Midsomer Murders</display-name>
  </channel>
  <channel id="doctor-who-classic">
    <display-name lang="es">Doctor Who Classic</display-name>
  </channel>
  <channel id="antiques-roadshow-uk">
    <display-name lang="es">Antiques Roadshow UK</display-name>
  </channel>
  <channel id="logo-pluto-tv">
    <display-name lang="es">Logo Pluto TV</display-name>
  </channel>
  <channel id="nfl-channel">
    <display-name lang="es">NFL Channel</display-name>
  </channel>
  <channel id="pluto-tv-cine-estelar">
    <display-name lang="es">Pluto TV Cine Estelar</display-name>
  </channel>
  <channel id="pluto-tv-cine-1">
    <display-name lang="es">Pluto TV Cine</display-name>
  </channel>
  <channel id="pluto-tv-investiga">
    <display-name lang="es">Pluto TV Investiga</display-name>
  </channel>
  <channel id="telemundo-telenovelas">
    <display-name lang="es">Telemundo Telenovelas</display-name>
  </channel>
  <channel id="mtv-latino">
    <display-name lang="es">MTV Latino</display-name>
  </channel>
  <channel id="comedy-central-latino">
    <display-name lang="es">Comedy Central Latino</display-name>
  </channel>
  <channel id="totally-turtles">
    <display-name lang="es">TOTALLY TURTLES</display-name>
  </channel>
  <channel id="dora-tv">
    <display-name lang="es">Dora TV</display-name>
  </channel>
  <channel id="yo-mtv">
    <display-name lang="es">Yo! MTV</display-name>
  </channel>
  <channel id="mtv-biggest-pop">
    <display-name lang="es">MTV Biggest Pop</display-name>
  </channel>
  <channel id="mtv-spankin-new">
    <display-name lang="es">MTV Spankin' New</display-name>
  </channel>
  <channel id="mtv-block-party">
    <display-name lang="es">MTV Block Party</display-name>
  </channel>
  <channel id="dallas-cowboys-cheerleaders">
    <display-name lang="es">Dallas Cowboys Cheer</display-name>
  </channel>
  <channel id="tv-land-drama">
    <display-name lang="es">TV Land Drama</display-name>
  </channel>
  <channel id="wild-n-out">
    <display-name lang="es">Wild 'N Out</display-name>
  </channel>
  <channel id="the-challenge">
    <display-name lang="es">The Challenge</display-name>
  </channel>
  <channel id="the-first">
    <display-name lang="es">The First</display-name>
  </channel>
  <channel id="tbn">
    <display-name lang="es">TBN</display-name>
  </channel>
  <channel id="hillsong-channel">
    <display-name lang="es">Hillsong Channel</display-name>
  </channel>
  <channel id="pursuitup">
    <display-name lang="es">PursuitUP</display-name>
  </channel>
  <channel id="pluto-tv-007">
    <display-name lang="es">Pluto TV 007</display-name>
  </channel>
  <channel id="gameplay-roblox">
    <display-name lang="es">Gameplay: Roblox</display-name>
  </channel>
  <channel id="love-and-hip-hop">
    <display-name lang="es">Love \u0026 Hip Hop</display-name>
  </channel>
  <channel id="black-ink-crew">
    <display-name lang="es">Black Ink Crew</display-name>
  </channel>
  <channel id="bet-her">
    <display-name lang="es">BET Her</display-name>
  </channel>
  <channel id="this-old-house">
    <display-name lang="es">This Old House</display-name>
  </channel>
  <channel id="today-1">
    <display-name lang="es">TODAY</display-name>
  </channel>
  <channel id="vh1-i-love-reality">
    <display-name lang="es">VH1 I Love Reality</display-name>
  </channel>
  <channel id="vh1-hip-hop-family">
    <display-name lang="es">VH1 Hip Hop Family</display-name>
  </channel>
  <channel id="american-gladiators">
    <display-name lang="es">American Gladiators</display-name>
  </channel>
  <channel id="baywatch">
    <display-name lang="es">Baywatch</display-name>
  </channel>
  <channel id="the-addams-family">
    <display-name lang="es">The Addams Family</display-name>
  </channel>
  <channel id="pluto-tv-lives">
    <display-name lang="es">Pluto TV Lives</display-name>
  </channel>
  <channel id="pluto-tv-reality">
    <display-name lang="es">Pluto TV Reality</display-name>
  </channel>
  <channel id="pluto-tv-celebrity">
    <display-name lang="es">Pluto TV Celebrity</display-name>
  </channel>
  <channel id="nick-latino">
    <display-name lang="es">Nick Latino</display-name>
  </channel>
  <channel id="nick-jr-latino">
    <display-name lang="es">Nick Jr. Latino</display-name>
  </channel>
  <channel id="pluto-tv-cocina">
    <display-name lang="es">Pluto TV Cocina</display-name>
  </channel>
  <channel id="pluto-tv-mundo">
    <display-name lang="es">Pluto TV Mundo</display-name>
  </channel>
  <channel id="pluto-tv-naturaleza">
    <display-name lang="es">Pluto TV Naturaleza</display-name>
  </channel>
  <channel id="spike-aventura">
    <display-name lang="es">Spike Aventura</display-name>
  </channel>
  <channel id="pluto-tv-cine-accion">
    <display-name lang="es">Pluto TV Cine Acción</display-name>
  </channel>
  <channel id="pluto-tv-cine-terror">
    <display-name lang="es">Pluto TV Cine Terror</display-name>
  </channel>
  <channel id="pluto-tv-realities-esp">
    <display-name lang="es">Pluto TV Realities ESP</display-name>
  </channel>
  <channel id="pluto-tv-007-en-espanol">
    <display-name lang="es">Pluto TV 007 en Español</display-name>
  </channel>
  <channel id="vevo-pop">
    <display-name lang="es">Vevo Pop</display-name>
  </channel>
  <channel id="leverage">
    <display-name lang="es">Leverage</display-name>
  </channel>
  <channel id="naruto">
    <display-name lang="es">Naruto</display-name>
  </channel>
  <channel id="vevo-country">
    <display-name lang="es">Vevo Country</display-name>
  </channel>
  <channel id="vevo-randb">
    <display-name lang="es">Vevo R\u0026B</display-name>
  </channel>
  <channel id="tosh-1">
    <display-name lang="es">Tosh.0</display-name>
  </channel>
  <channel id="pocketwatch">
    <display-name lang="es">pocket.watch</display-name>
  </channel>
  <channel id="court-tv-1">
    <display-name lang="es">Court TV</display-name>
  </channel>
  <channel id="pluto-tv-kids-animation">
    <display-name lang="es">Pluto TV Kids Animation</display-name>
  </channel>
  <channel id="pluto-tv-tween-1">
    <display-name lang="es">Pluto TV Tween</display-name>
  </channel>
  <channel id="pluto-tv-action-sports">
    <display-name lang="es">Pluto TV Action Sports</display-name>
  </channel>
  <channel id="et-live">
    <display-name lang="es">ET Live</display-name>
  </channel>
  <channel id="lively-place">
    <display-name lang="es">Lively Place</display-name>
  </channel>
  <channel id="cbsn-new-york">
    <display-name lang="es">CBSN New York</display-name>
  </channel>
  <channel id="cbsn-los-angeles">
    <display-name lang="es">CBSN Los Angeles</display-name>
  </channel>
  <channel id="cmt-pluto-tv">
    <display-name lang="es">CMT Pluto TV</display-name>
  </channel>
  <channel id="pga-tour">
    <display-name lang="es">PGA TOUR</display-name>
  </channel>
  <channel id="fubo-sports-network">
    <display-name lang="es">fubo Sports Network</display-name>
  </channel>
  <channel id="bein-sports-xtra">
    <display-name lang="es">beIN SPORTS XTRA</display-name>
  </channel>
  <channel id="nbc-news-now">
    <display-name lang="es">NBC News NOW</display-name>
  </channel>
  <channel id="americas-voice">
    <display-name lang="es">America's Voice News</display-name>
  </channel>
  <channel id="cops">
    <display-name lang="es">COPS</display-name>
  </channel>
  <channel id="blaze-live">
    <display-name lang="es">Blaze Live</display-name>
  </channel>
  <channel id="one-day-at-a-time">
    <display-name lang="es">One Day at a Time</display-name>
  </channel>
  <channel id="people-are-awesome">
    <display-name lang="es">People Are Awesome</display-name>
  </channel>
  <channel id="game-show-central">
    <display-name lang="es">Game Show Central</display-name>
  </channel>
  <channel id="narco-novelas">
    <display-name lang="es">Narco Novelas</display-name>
  </channel>
  <channel id="nuestra-vision">
    <display-name lang="es">Nuestra Vision</display-name>
  </channel>
  <channel id="johnny-carson-tv">
    <display-name lang="es">Johnny Carson TV</display-name>
  </channel>
  <channel id="awe-encore">
    <display-name lang="es">AWE Encore</display-name>
  </channel>
  <channel id="oan-encore">
    <display-name lang="es">OAN Encore</display-name>
  </channel>
  <channel id="all-reality-by-we-tv">
    <display-name lang="es">All Reality by WE tv</display-name>
  </channel>
  <channel id="stories-by-amc">
    <display-name lang="es">Stories by AMC</display-name>
  </channel>
  <channel id="slightly-off-by-ifc">
    <display-name lang="es">Slightly Off By IFC</display-name>
  </channel>
  <channel id="the-rifleman">
    <display-name lang="es">The Rifleman</display-name>
  </channel>
  <channel id="afv-tv">
    <display-name lang="es">AFV TV</display-name>
  </channel>
  <channel id="the-walking-dead-esp">
    <display-name lang="es">The Walking Dead ESP</display-name>
  </channel>
  <channel id="novelas-romance">
    <display-name lang="es">Novelas Romance</display-name>
  </channel>
  <channel id="novelas-drama">
    <display-name lang="es">Novelas Drama</display-name>
  </channel>
  <channel id="novelas-thriller">
    <display-name lang="es">Novelas Thriller</display-name>
  </channel>
  <channel id="americas-test-kitchen">
    <display-name lang="es">America's Test Kitchen</display-name>
  </channel>
  <channel id="western-tv">
    <display-name lang="es">Western TV</display-name>
  </channel>
  <channel id="forensic-files-en-esp-1">
    <display-name lang="es">Forensic Files en ESP</display-name>
  </channel>
  <channel id="deal-or-no-deal">
    <display-name lang="es">Deal or No Deal</display-name>
  </channel>
  <channel id="judge-nosey">
    <display-name lang="es">Judge Nosey</display-name>
  </channel>
  <channel id="cbs-sports-hq">
    <display-name lang="es">CBS Sports HQ</display-name>
  </channel>
  <channel id="cbsn-bay-area">
    <display-name lang="es">CBSN Bay Area</display-name>
  </channel>
  <channel id="little-baby-bum">
    <display-name lang="es">Little Baby Bum</display-name>
  </channel>
  <channel id="bellator-mma">
    <display-name lang="es">Bellator MMA</display-name>
  </channel>
  <channel id="dabl">
    <display-name lang="es">Dabl</display-name>
  </channel>
  <channel id="dark-shadows">
    <display-name lang="es">Dark Shadows</display-name>
  </channel>
  <channel id="the-carol-burnett-show">
    <display-name lang="es">The Carol Burnett Show</display-name>
  </channel>
  <channel id="threes-company">
    <display-name lang="es">Three's Company</display-name>
  </channel>
  <channel id="csi">
    <display-name lang="es">CSI</display-name>
  </channel>
  <channel id="star-trek-1">
    <display-name lang="es">Star Trek</display-name>
  </channel>
  <channel id="demand-africa">
    <display-name lang="es">Demand Africa</display-name>
  </channel>
  <channel id="loupe">
    <display-name lang="es">Loupe</display-name>
  </channel>
  <channel id="pluto-tv-love-stories">
    <display-name lang="es">Pluto TV Love Stories</display-name>
  </channel>
  <channel id="pluto-tv-suspense">
    <display-name lang="es">Pluto TV Suspense</display-name>
  </channel>
  <channel id="classic-tv-comedy">
    <display-name lang="es">Classic TV Comedy</display-name>
  </channel>
  <channel id="classic-tv-drama-ptv1">
    <display-name lang="es">Classic TV Drama</display-name>
  </channel>
  <channel id="gamespot">
    <display-name lang="es">GameSpot</display-name>
  </channel>
  <channel id="black-news-channel">
    <display-name lang="es">Black News Channel</display-name>
  </channel>
  <channel id="survivor-ptv1">
    <display-name lang="es">Survivor</display-name>
  </channel>
  <channel id="rescue-911">
    <display-name lang="es">Rescue 911</display-name>
  </channel>
  <channel id="the-amazing-race">
    <display-name lang="es">The Amazing Race</display-name>
  </channel>
  <channel id="pluto-tv-drama-life">
    <display-name lang="es">Pluto TV Drama Life</display-name>
  </channel>
  <channel id="pluto-tv-crime-drama">
    <display-name lang="es">Pluto TV Crime Drama</display-name>
  </channel>
  <channel id="vevo-70s">
    <display-name lang="es">Vevo '70s</display-name>
  </channel>
  <channel id="vevo-reggaeton-and-trap">
    <display-name lang="es">Vevo Reggaetón \u0026 Trap</display-name>
  </channel>
  <channel id="the-bob-ross-channel">
    <display-name lang="es">The Bob Ross Channel</display-name>
  </channel>
  <channel id="90210">
    <display-name lang="es">90210</display-name>
  </channel>
  <channel id="pluto-tv-crime-movies">
    <display-name lang="es">Pluto TV Crime Movies</display-name>
  </channel>
  <channel id="pluto-tv-staff-picks">
    <display-name lang="es">Pluto TV Staff Picks</display-name>
  </channel>
  <channel id="90s-throwback">
    <display-name lang="es">90s Throwback</display-name>
  </channel>
  <channel id="70s-cinema">
    <display-name lang="es">70s Cinema</display-name>
  </channel>
  <channel id="unsolved-mysteries-esp">
    <display-name lang="es">Unsolved Mysteries ESP</display-name>
  </channel>
  <channel id="the-design-network">
    <display-name lang="es">The Design Network</display-name>
  </channel>
  <channel id="cmt-equal-play">
    <display-name lang="es">CMT Equal Play</display-name>
  </channel>
  <channel id="narcos">
    <display-name lang="es">Narcos</display-name>
  </channel>
  <channel id="narcos-en-espanol">
    <display-name lang="es">Narcos en Español</display-name>
  </channel>
</tv>